gen_reg.v
/*
CS 274
Ursinus College

@author Michael Cummins
@purpose Implementation of 6 general registers
*/

module gen_reg(
    input wire clk,
    input wire [1:0] addr_sel, // Address selection (0 for full, 1 for higher bits, 2 for lower bits)
    input wire [9:0] addr,     // Address to read/write data
    input wire [19:0] data_in,  // Data to be written into register
    output reg [19:0] data_out  // Data read from the selected register
);

reg [19:0] registers [5:0]; // Array of six 20-bit registers

always @(posedge clk) begin
    case (addr_sel)
        2'b00: // Full word access
            if (addr < 6) begin
                data_out <= registers[addr];
            end
        2'b01: // Higher 10 bits access
            if (addr < 6) begin
                data_out <= registers[addr][19:10];
            end
        2'b10: // Lower 10 bits access
            if (addr < 6) begin
                data_out <= registers[addr][9:0];
            end
        default:
            data_out <= 20'h0; // Default output to 0 if invalid address selection
    endcase
end

always @(posedge clk) begin
    if (addr_sel == 2'b00 && addr < 6) begin
        registers[addr] <= data_in;
    end
    else if (addr_sel == 2'b01 && addr < 6) begin
        registers[addr][19:10] <= data_in;
    end
    else if (addr_sel == 2'b10 && addr < 6) begin
        registers[addr][9:0] <= data_in;
    end
end

endmodule

gen_reg_tb.v
/*
CS 274
Ursinus College

@author Michael Cummins
@purpose Implementation of 6 general registers
*/

`include "gen_reg.v"
`default_nettype none
`timescale 1ns / 1ns

module gen_reg_tb;

    parameter CLK_PERIOD = 10;
    
    reg clk;
    reg [1:0] addr_sel;
    reg [9:0] addr;
    reg [19:0] data_in;
    wire [19:0] data_out;
    
    gen_reg x0 (
        .clk(clk),
        .addr_sel(addr_sel),
        .addr(addr),
        .data_in(data_in),
        .data_out(data_out)
    );
    
    always #((CLK_PERIOD / 2)) clk = ~clk;
    
    initial begin
        clk = 0;
        addr_sel = 2'b00; // Full word access
        
        $dumpfile("gen_reg_tb");
        $dumpvars(1,x0);

        // Write data to register 0
        addr = 0;
        data_in = 20'b10101010101010101010;
        #10;
        
        // Read data from register 0
        addr = 0;
        #10;
        $display("Data from register 0 (Full word access): %h", data_out);
        
        // Write data to register 1 (Higher 10 bits)
        addr_sel = 2'b01;
        addr = 1;
        data_in = 20'b11001100110011001100;
        #10;
        
        // Read data from register 1 (Higher 10 bits)
        addr = 1;
        #10;
        $display("Data from register 1 (Higher 10 bits): %h", data_out);
        
        // Write data to register 2 (Lower 10 bits)
        addr_sel = 2'b10;
        addr = 2;
        data_in = 20'b11110000111100001111;
        #10;
        
        // Read data from register 2 (Lower 10 bits)
        addr = 2;
        #10;
        $display("Data from register 2 (Lower 10 bits): %h", data_out);
        
        // End simulation
        $finish;
    end
    
endmodule

gen_reg_tb.vcd
$date
	Thu Mar 21 16:46:02 2024
$end
$version
	Icarus Verilog
$end
$timescale
	1ns
$end
$scope module gen_reg_tb $end
$scope module x0 $end
$var wire 10 ! addr [9:0] $end
$var wire 2 " addr_sel [1:0] $end
$var wire 1 # clk $end
$var wire 20 $ data_in [19:0] $end
$var reg 20 % data_out [19:0] $end
$upscope $end
$upscope $end
$enddefinitions $end
$comment Show the parameter values. $end
$dumpall
$end
#0
$dumpvars
bx %
b10101010101010101010 $
0#
b0 "
b0 !
$end
#5
1#
#10
0#
#15
b10101010101010101010 %
1#
#20
0#
b11001100110011001100 $
b1 !
b1 "
#25
b0xxxxxxxxxx %
1#
#30
0#
#35
b11001100 %
1#
#40
0#
b11110000111100001111 $
b10 !
b10 "
#45
b0xxxxxxxxxx %
1#
#50
0#
#55
b1100001111 %
1#
