Inc_Reg/inc_reg.v
/*
CS 274
Ursinus College

@author Michael Cummins
@purpose Implementation of increment registers
*/

module inc_reg(
    input clk,            
    input reset,          
    input instruction_complete, 
    input mem_access,     
    input mem_correction, 
    output reg [19:0] instruction_count, 
    output reg [19:0] memory_access_count, 
    output reg [19:0] memory_correction_count 
);

always @(posedge clk or posedge reset) begin
    if (reset) begin
        instruction_count <= 20'b0;
        memory_access_count <= 20'b0;
        memory_correction_count <= 20'b0;
    end else begin
        if (instruction_complete) begin
            instruction_count <= instruction_count + 1;
        end
        if (mem_access) begin
            memory_access_count <= memory_access_count + 1;
        end
        if (mem_correction) begin
            memory_correction_count <= memory_correction_count + 1;
        end
    end
end

endmodule

inc_reg_tb.v
/*
CS 274
Ursinus College

@author Michael Cummins
@purpose Implementation of increment registers
*/

`include "inc_reg.v"
`default_nettype none
`timescale 1ns / 1ns

module inc_reg_tb;

    parameter CLK_PERIOD = 10;

    reg clk;
    reg reset;
    reg instruction_complete;
    reg mem_access;
    reg mem_correction;
    wire [19:0] instruction_count;
    wire [19:0] memory_access_count;
    wire [19:0] memory_correction_count;

    inc_reg x0 (
        .clk(clk),
        .reset(reset),
        .instruction_complete(instruction_complete),
        .mem_access(mem_access),
        .mem_correction(mem_correction),
        .instruction_count(instruction_count),
        .memory_access_count(memory_access_count),
        .memory_correction_count(memory_correction_count)
    );

     always #((CLK_PERIOD / 2)) clk = ~clk;

    initial begin
        clk = 0;

        $dumpfile("inc_reg_tb");
        $dumpvars(1,x0);

        reset = 1;

        instruction_complete = 0;
        mem_access = 0;
        mem_correction = 0;

        #20 reset = 0;
        #100;

        instruction_complete = 1;
        #10;
        instruction_complete = 0; 
        #10;

        mem_access = 1;
        #10;
        mem_access = 0; 
        #10;

        mem_correction = 1;
        #10;
        mem_correction = 0; 
        #10

        $finish;
    end

endmodule

inc_reg_tb.vcd
$date
	Thu Mar 21 16:48:15 2024
$end
$version
	Icarus Verilog
$end
$timescale
	1ns
$end
$scope module inc_reg_tb $end
$scope module x0 $end
$var wire 1 ! clk $end
$var wire 1 " instruction_complete $end
$var wire 1 # mem_access $end
$var wire 1 $ mem_correction $end
$var wire 1 % reset $end
$var reg 20 & instruction_count [19:0] $end
$var reg 20 ' memory_access_count [19:0] $end
$var reg 20 ( memory_correction_count [19:0] $end
$upscope $end
$upscope $end
$enddefinitions $end
$comment Show the parameter values. $end
$dumpall
$end
#0
$dumpvars
b0 (
b0 '
b0 &
1%
0$
0#
0"
0!
$end
#5
1!
#10
0!
#15
1!
#20
0!
0%
#25
1!
#30
0!
#35
1!
#40
0!
#45
1!
#50
0!
#55
1!
#60
0!
#65
1!
#70
0!
#75
1!
#80
0!
#85
1!
#90
0!
#95
1!
#100
0!
#105
1!
#110
0!
#115
1!
#120
0!
1"
#125
b1 &
1!
#130
0!
0"
#135
1!
#140
0!
1#
#145
b1 '
1!
#150
0!
0#
#155
1!
#160
0!
1$
#165
b1 (
1!
#170
0!
0$
